{"term_results": [{"entry_eng": "Tourists – 529", "entry_rus": "туристов – 529", "definition_eng": "Information", "definition_rus": "Информация", "synonyms_eng": [], "synonyms_rus": []}, {"entry_eng": "Tourists – 74", "entry_rus": "туристов – 74", "definition_eng": "Information", "definition_rus": "Информация", "synonyms_eng": [], "synonyms_rus": []}, {"entry_eng": "Tourists — 1,470", "entry_rus": "туристов 1 470", "definition_eng": "Information", "definition_rus": "Информация", "synonyms_eng": [], "synonyms_rus": []}, {"entry_eng": "Tourists — 1,933", "entry_rus": "туристов 1 933", "definition_eng": "Information", "definition_rus": "Информация", "synonyms_eng": [], "synonyms_rus": []}, {"entry_eng": "Tourists — 216", "entry_rus": "туристов 216", "definition_eng": "Information", "definition_rus": "Информация", "synonyms_eng": [], "synonyms_rus": []}, {"entry_eng": "toward one of the CPSU leaders", "entry_rus": "в отношении одного из руководителей КПСС", "definition_eng": "Actors; institutional.", "definition_rus": "Акторы; институциональное.", "synonyms_eng": ["toward one of the CPSU leaders"], "synonyms_rus": ["в отношении одного из руководителей КПСС"]}, {"entry_eng": "toward the broadcast", "entry_rus": "к показу", "definition_eng": "Actions", "definition_rus": "Действия", "synonyms_eng": ["toward the broadcast"], "synonyms_rus": ["к показу"]}, {"entry_eng": "towards the decisions of the January (1987)", "entry_rus": "к решениям январского (1987 года)", "definition_eng": "Documents; institutional.", "definition_rus": "Документы; институциональное.", "synonyms_eng": ["towards the decisions of the January (1987)"], "synonyms_rus": ["к решениям январского (1987 года)"]}, {"entry_eng": "trainee", "entry_rus": "стажера", "definition_eng": "Actors", "definition_rus": "Акторы", "synonyms_eng": ["trainee"], "synonyms_rus": ["стажера"]}, {"entry_eng": "trainees", "entry_rus": "стажеров", "definition_eng": "Actors", "definition_rus": "Акторы", "synonyms_eng": ["trainees"], "synonyms_rus": ["стажеров"]}, {"entry_eng": "traitors to the Motherland", "entry_rus": "изменников Родины", "definition_eng": "Actors; discrediting.", "definition_rus": "Акторы; дискредитация.", "synonyms_eng": ["traitors to the Motherland"], "synonyms_rus": ["изменников Родины"]}, {"entry_eng": "traveling the Pavlohrad–Sosnovka route", "entry_rus": "следовавшим по маршруту Павлоград — Сосновка", "definition_eng": "Actions", "definition_rus": "Действия", "synonyms_eng": ["traveling the Pavlohrad–Sosnovka route"], "synonyms_rus": ["следовавшим по маршруту Павлоград — Сосновка"]}, {"entry_eng": "treason against the Motherland", "entry_rus": "измена Родине", "definition_eng": "Legal; institutional.", "definition_rus": "Юридическое; институциональное.", "synonyms_eng": ["treason against the Motherland"], "synonyms_rus": ["измена Родине"]}, {"entry_eng": "two cabins were damaged", "entry_rus": "две каюты", "definition_eng": "Status", "definition_rus": "Статус", "synonyms_eng": ["two cabins were damaged"], "synonyms_rus": ["две каюты"]}, {"entry_eng": "two from Greece — 56", "entry_rus": "два из Греции 56", "definition_eng": "Information", "definition_rus": "Информация", "synonyms_eng": [], "synonyms_rus": []}, {"entry_eng": "two from Italy — 41", "entry_rus": "два из Италии 41", "definition_eng": "Information", "definition_rus": "Информация", "synonyms_eng": [], "synonyms_rus": []}, {"entry_eng": "two from Lebanon — 55", "entry_rus": "два из Ливана – 55", "definition_eng": "Information", "definition_rus": "Информация", "synonyms_eng": [], "synonyms_rus": []}, {"entry_eng": "two from Liberia — 73", "entry_rus": "два из Либерии 73", "definition_eng": "Information", "definition_rus": "Информация", "synonyms_eng": [], "synonyms_rus": []}, {"entry_eng": "two from Panama — 34", "entry_rus": "два из Панамы 34", "definition_eng": "Information", "definition_rus": "Информация", "synonyms_eng": [], "synonyms_rus": []}, {"entry_eng": "Two of them committed suicide", "entry_rus": "Некоторые из них покончили жизнь самоубийством", "definition_eng": "Events", "definition_rus": "События", "synonyms_eng": ["Two of them committed suicide"], "synonyms_rus": ["Некоторые из них покончили жизнь самоубийством"]}]}