{
  "term_results": [
    {"entry_eng": "calls to declare the republic a nuclear-free zone", "entry_rus": "призывы объявить республику безъядерной зоной", "definition_eng": "Action; calls for nuclear-free zone status.", "definition_rus": "Действие; призывы объявить республику безъядерной зоной.", "synonyms_eng": ["calls to declare the republic nuclear-free", "calls for nuclear-free zone", "appeals for denuclearization"], "synonyms_rus": ["призывы объявить республику безъядерной зоной", "призывы к безъядерному статусу", "требования денуклеаризации"]},
    {"entry_eng": "Canada", "entry_rus": "Канаде", "definition_eng": "Geographic reference; Canada (locative).", "definition_rus": "Географическая отсылка; Канада.", "synonyms_eng": ["Canada", "in Canada", "Canadian"], "synonyms_rus": ["Канаде", "в Канаде", "канадский"]},
    {"entry_eng": "Canada", "entry_rus": "из Канады", "definition_eng": "Geographic reference; from Canada.", "definition_rus": "Географическая отсылка; из Канады.", "synonyms_eng": ["Canada", "from Canada", "Canadian"], "synonyms_rus": ["из Канады", "из Канады", "канадский"]},
    {"entry_eng": "Canada – 14", "entry_rus": "Канада – 14", "definition_eng": "Statistical formulation; Canada, count 14.", "definition_rus": "Статистическая формулировка; Канада — 14.", "synonyms_eng": [], "synonyms_rus": []},
    {"entry_eng": "Canada — 13", "entry_rus": "из Канады 13", "definition_eng": "Statistical formulation; 13 from Canada.", "definition_rus": "Статистическая формулировка; 13 из Канады.", "synonyms_eng": [], "synonyms_rus": []},
    {"entry_eng": "Canada — 267", "entry_rus": "из Канады 267", "definition_eng": "Statistical formulation; 267 from Canada.", "definition_rus": "Статистическая формулировка; 267 из Канады.", "synonyms_eng": [], "synonyms_rus": []},
    {"entry_eng": "Canada — 34", "entry_rus": "из Канады 34", "definition_eng": "Statistical formulation; 34 from Canada.", "definition_rus": "Статистическая формулировка; 34 из Канады.", "synonyms_eng": [], "synonyms_rus": []},
    {"entry_eng": "Canada — 7", "entry_rus": "Канады – 7", "definition_eng": "Statistical formulation; Canada, 7.", "definition_rus": "Статистическая формулировка; Канады — 7.", "synonyms_eng": [], "synonyms_rus": []},
    {"entry_eng": "Canada's Ministry of Manpower and Immigration", "entry_rus": "министерство рабочей силы и иммиграции Канады", "definition_eng": "Institutional actor; Canadian immigration ministry.", "definition_rus": "Институциональный актор; министерство труда и иммиграции Канады.", "synonyms_eng": ["Canada's Ministry of Manpower and Immigration", "Canadian Immigration Ministry", "Employment and Immigration Canada"], "synonyms_rus": ["министерство рабочей силы и иммиграции Канады", "канадское министерство иммиграции", "Минтруд и иммиграция Канады"]},
    {"entry_eng": "cand the ompromised foreign national centers", "entry_rus": "компрометацию зарубежных наццентров", "definition_eng": "Discrediting action; compromising foreign nationalist centers (entry has typo: cand/ompromised).", "definition_rus": "Дискредитирующее действие; компрометация зарубежных националистических центров.", "synonyms_eng": ["and compromising foreign national centers", "compromising overseas nationalist centers", "discrediting émigré centers"], "synonyms_rus": ["компрометацию зарубежных наццентров", "дискредитацию эмигрантских центров", "компрометацию националистических центров"]},
    {"entry_eng": "carried out", "entry_rus": "осуществили", "definition_eng": "Action; carried out.", "definition_rus": "Действие; осуществили.", "synonyms_eng": ["carried out", "conducted", "implemented"], "synonyms_rus": ["осуществили", "провели", "выполнили"]},
    {"entry_eng": "caused confusion", "entry_rus": "вызвали растерянность", "definition_eng": "Discrediting outcome; caused confusion.", "definition_rus": "Дискредитирующий исход; вызвали растерянность.", "synonyms_eng": ["caused confusion", "provoked confusion", "led to disarray"], "synonyms_rus": ["вызвали растерянность", "привели к растерянности", "спровоцировали замешательство"]},
    {"entry_eng": "ceased unlawful activities", "entry_rus": "прекратил противоправную деятельность", "definition_eng": "Legal action; ceased unlawful activities.", "definition_rus": "Правовое действие; прекратил противоправную деятельность.", "synonyms_eng": ["ceased unlawful activities", "stopped illegal activities", "discontinued unlawful conduct"], "synonyms_rus": ["прекратил противоправную деятельность", "прекратил незаконную деятельность", "прекратил противоправные действия"]},
    {"entry_eng": "centers of ideological subversion", "entry_rus": "центров идеологической диверсии", "definition_eng": "Discrediting designation; centers of ideological subversion.", "definition_rus": "Дискредитирующее обозначение; центры идеологической диверсии.", "synonyms_eng": ["centers of ideological subversion", "ideological subversion centers", "centers of ideological sabotage"], "synonyms_rus": ["центров идеологической диверсии", "центров подрывной деятельности", "очагов идеологической диверсии"]},
    {"entry_eng": "Central Committee of the Communist Party of Ukraine", "entry_rus": "Центральный Комитет Коммунистической партии Украины", "definition_eng": "Institutional actor; CPU Central Committee.", "definition_rus": "Институциональный актор; ЦК КПУ.", "synonyms_eng": ["Central Committee of the Communist Party of Ukraine", "CPU Central Committee", "CC of the Communist Party of Ukraine"], "synonyms_rus": ["Центральный Комитет КПУ", "ЦК Коммунистической партии Украины", "ЦК КПУ"]},
    {"entry_eng": "Central Committee of the Communist Party of Ukraine", "entry_rus": "Центральный Комитет Компартии Украины", "definition_eng": "Same; abbreviated form.", "definition_rus": "То же; сокращённая форма.", "synonyms_eng": ["Central Committee of the Communist Party of Ukraine", "CPU Central Committee", "CC CPU"], "synonyms_rus": ["Центральный Комитет Компартии Украины", "ЦК Компартии Украины", "ЦК КПУ"]},
    {"entry_eng": "Central Committee of the Communist Party of Ukraine", "entry_rus": "Центральный комитет Коммунистической партии Украины", "definition_eng": "Same; lowercase комитет.", "definition_rus": "То же; комитет с маленькой буквы.", "synonyms_eng": ["Central Committee of the Communist Party of Ukraine", "CPU Central Committee", "CC CPU"], "synonyms_rus": ["Центральный комитет КПУ", "ЦК КПУ", "центральный комитет"]},
    {"entry_eng": "Central Committee of the Communist Party of Ukraine", "entry_rus": "ЦК Компартии Украины", "definition_eng": "Same; abbreviated ЦК.", "definition_rus": "То же; сокращение ЦК.", "synonyms_eng": ["Central Committee of the Communist Party of Ukraine", "CC CPU", "TsK KPU"], "synonyms_rus": ["ЦК Компартии Украины", "ЦК КПУ", "Центральный комитет"]},
    {"entry_eng": "certain documents, discovered in the archives [...] were used", "entry_rus": "использованы обнаруженные в архиве отдельные документы", "definition_eng": "Document usage; archive documents used.", "definition_rus": "Использование документов; использованы архивные документы.", "synonyms_eng": ["certain documents discovered in the archives were used", "archive documents were utilized", "documents found in archives were used"], "synonyms_rus": ["использованы обнаруженные в архиве документы", "применены архивные документы", "использованы архивные материалы"]},
    {"entry_eng": "Chairman of the Committee", "entry_rus": "Председатель Комитета", "definition_eng": "Institutional role; Committee Chairman.", "definition_rus": "Институциональная роль; председатель комитета.", "synonyms_eng": ["Chairman of the Committee", "Committee Chairman", "Committee head"], "synonyms_rus": ["Председатель Комитета", "председатель комитета", "глава комитета"]}
  ]
}
