{
  "term_results": [
    {"entry_eng": "born 1909", "entry_rus": "1909 года рождения", "definition_eng": "Biographical datum; year of birth 1909.", "definition_rus": "Биографическая справка; 1909 г.р.", "synonyms_eng": [], "synonyms_rus": []},
    {"entry_eng": "born 1917", "entry_rus": "1917 года рождения", "definition_eng": "Biographical datum; year of birth 1917.", "definition_rus": "Биографическая справка; 1917 г.р.", "synonyms_eng": [], "synonyms_rus": []},
    {"entry_eng": "born 1919", "entry_rus": "1919 года рождения", "definition_eng": "Biographical datum; year of birth 1919.", "definition_rus": "Биографическая справка; 1919 г.р.", "synonyms_eng": [], "synonyms_rus": []},
    {"entry_eng": "born 1931", "entry_rus": "1931 года рождения", "definition_eng": "Biographical datum; year of birth 1931.", "definition_rus": "Биографическая справка; 1931 г.р.", "synonyms_eng": [], "synonyms_rus": []},
    {"entry_eng": "born 1939", "entry_rus": "1939 года рождения", "definition_eng": "Biographical datum; year of birth 1939.", "definition_rus": "Биографическая справка; 1939 г.р.", "synonyms_eng": [], "synonyms_rus": []},
    {"entry_eng": "born 1950", "entry_rus": "1950 года рождения", "definition_eng": "Biographical datum; year of birth 1950.", "definition_rus": "Биографическая справка; 1950 г.р.", "synonyms_eng": [], "synonyms_rus": []},
    {"entry_eng": "born 1953", "entry_rus": "1953 года рождения", "definition_eng": "Biographical datum; year of birth 1953.", "definition_rus": "Биографическая справка; 1953 г.р.", "synonyms_eng": [], "synonyms_rus": []},
    {"entry_eng": "born 1957", "entry_rus": "1957 года рождения", "definition_eng": "Biographical datum; year of birth 1957.", "definition_rus": "Биографическая справка; 1957 г.р.", "synonyms_eng": [], "synonyms_rus": []},
    {"entry_eng": "born 1963", "entry_rus": "1963 года рождения", "definition_eng": "Biographical datum; year of birth 1963.", "definition_rus": "Биографическая справка; 1963 г.р.", "synonyms_eng": [], "synonyms_rus": []},
    {"entry_eng": "born 1964", "entry_rus": "1964 года рождения", "definition_eng": "Biographical datum; year of birth 1964.", "definition_rus": "Биографическая справка; 1964 г.р.", "synonyms_eng": [], "synonyms_rus": []},
    {"entry_eng": "born 1965", "entry_rus": "1965 года рождения", "definition_eng": "Biographical datum; year of birth 1965.", "definition_rus": "Биографическая справка; 1965 г.р.", "synonyms_eng": [], "synonyms_rus": []},
    {"entry_eng": "born in 1930", "entry_rus": "1930 года рождения", "definition_eng": "Biographical datum; year of birth 1930.", "definition_rus": "Биографическая справка; 1930 г.р.", "synonyms_eng": [], "synonyms_rus": []},
    {"entry_eng": "born in 1931", "entry_rus": "1931 года рождения", "definition_eng": "Biographical datum; year of birth 1931.", "definition_rus": "Биографическая справка; 1931 г.р.", "synonyms_eng": [], "synonyms_rus": []},
    {"entry_eng": "born in 1938", "entry_rus": "1938 года рождения", "definition_eng": "Biographical datum; year of birth 1938.", "definition_rus": "Биографическая справка; 1938 г.р.", "synonyms_eng": [], "synonyms_rus": []},
    {"entry_eng": "born in 1942", "entry_rus": "1942 года рождения", "definition_eng": "Biographical datum; year of birth 1942.", "definition_rus": "Биографическая справка; 1942 г.р.", "synonyms_eng": [], "synonyms_rus": []},
    {"entry_eng": "both had one dependent child", "entry_rus": "имевшие на иждивении по одному ребенку", "definition_eng": "Familial status; each had one dependent child.", "definition_rus": "Семейный статус; имевшие на иждивении по одному ребёнку.", "synonyms_eng": ["both had one dependent child", "each with one dependent", "each supporting one child"], "synonyms_rus": ["имевшие на иждивении по одному ребёнку", "с одним иждивенцем каждый", "по одному ребёнку на иждивении"]},
    {"entry_eng": "both members of the Komsomol (VLKSM)", "entry_rus": "оба члены ВЛКСМ", "definition_eng": "Status; both Komsomol members.", "definition_rus": "Статус; оба члены ВЛКСМ.", "synonyms_eng": ["both members of the Komsomol", "both Komsomol members", "both in VLKSM"], "synonyms_rus": ["оба члены ВЛКСМ", "оба комсомольцы", "оба в комсомоле"]},
    {"entry_eng": "Both ships remain seaworthy", "entry_rus": "Суда находятся в мореходном состоянии", "definition_eng": "Status; ships are seaworthy.", "definition_rus": "Статус; суда в мореходном состоянии.", "synonyms_eng": ["Both ships remain seaworthy", "Both vessels are seaworthy", "Ships are in operational condition"], "synonyms_rus": ["Суда находятся в мореходном состоянии", "Суда мореходны", "Судна в исправности"]},
    {"entry_eng": "brochures", "entry_rus": "и брошюр (1985 г.- 82)", "definition_eng": "Material; brochures with year/count.", "definition_rus": "Материал; брошюры с указанием года и количества.", "synonyms_eng": ["brochures", "and brochures", "pamphlets"], "synonyms_rus": ["и брошюр", "брошюры", "печатных материалов"]},
    {"entry_eng": "brought to the outpost", "entry_rus": "доставил на заставу", "definition_eng": "Action; brought to the border outpost.", "definition_rus": "Действие; доставил на заставу.", "synonyms_eng": ["brought to the outpost", "delivered to the outpost", "taken to the border post"], "synonyms_rus": ["доставил на заставу", "привёз на заставу", "доставлен на погранзаставу"]}
  ]
}
